odoo/addons/partner_children_address_autocreate/README.rst
odoo/addons/partner_children_address_autocreate/__init__.py
odoo/addons/partner_children_address_autocreate/__manifest__.py
odoo/addons/partner_children_address_autocreate/i18n/es.po
odoo/addons/partner_children_address_autocreate/models/__init__.py
odoo/addons/partner_children_address_autocreate/models/res_partner.py
odoo/addons/partner_children_address_autocreate/readme/CONTRIBUTORS.md
odoo/addons/partner_children_address_autocreate/readme/DESCRIPTION.md
odoo/addons/partner_children_address_autocreate/readme/USAGE.md
odoo/addons/partner_children_address_autocreate/static/description/icon.png
odoo/addons/partner_children_address_autocreate/static/description/index.html
odoo/addons/partner_children_address_autocreate/tests/__init__.py
odoo/addons/partner_children_address_autocreate/tests/test_partner_children_address_autocreate.py
odoo_addon_partner_children_address_autocreate-17.0.1.0.0.1.dist-info/METADATA
odoo_addon_partner_children_address_autocreate-17.0.1.0.0.1.dist-info/WHEEL
odoo_addon_partner_children_address_autocreate-17.0.1.0.0.1.dist-info/top_level.txt
odoo_addon_partner_children_address_autocreate-17.0.1.0.0.1.dist-info/RECORD
